dataclassesdb/__init__.py
dataclassesdb-0.0.11.dist-info/LICENSE
dataclassesdb-0.0.11.dist-info/WHEEL
dataclassesdb-0.0.11.dist-info/METADATA
dataclassesdb-0.0.11.dist-info/RECORD
